{
  "id": "4931275",
  "name": "metamask",
  "font_family": "iconfont",
  "css_prefix_text": "icon-",
  "description": "",
  "glyphs": [
    {
      "icon_id": "5387735",
      "name": "眼睛_隐藏",
      "font_class": "yanjing_yincang",
      "unicode": "eb45",
      "unicode_decimal": 60229
    },
    {
      "icon_id": "5387736",
      "name": "眼睛_显示",
      "font_class": "yanjing_xianshi",
      "unicode": "eb46",
      "unicode_decimal": 60230
    },
    {
      "icon_id": "11372780",
      "name": "眼睛",
      "font_class": "yanjing",
      "unicode": "e8c7",
      "unicode_decimal": 59591
    }
  ]
}
